interdict/__init__.py
interdict-2020.11.1.dist-info/LICENSE
interdict-2020.11.1.dist-info/WHEEL
interdict-2020.11.1.dist-info/METADATA
interdict-2020.11.1.dist-info/RECORD
