Metadata-Version: 2.1
Name: interdict
Version: 2020.11.1
Summary: Dictionary filter
Home-page: https://github.com/whardier/interdict
License: MIT
Author: Shane R. Spencer
Author-email: 305301+whardier@users.noreply.github.com
Requires-Python: >=3.8,<4.0
Classifier: License :: OSI Approved :: MIT License
Classifier: Programming Language :: Python :: 3
Classifier: Programming Language :: Python :: 3.8
Classifier: Programming Language :: Python :: 3.9
Requires-Dist: flatten-dict
Project-URL: Funding, https://github.com/sponsors/whardier
Project-URL: Repository, https://github.com/whardier/interdict
